pypackit_test1/__init__.py
pypackit_test1/__main__.py
pypackit_test1/py.typed
pypackit_test1/data/__init__.py
pypackit_test1/data/__test_file__
pypackit_test1/exception/__init__.py
pypackit_test1/exception/data.py
PyPackIT_Test1-0.0.10.dist-info/LICENSE-MIT
PyPackIT_Test1-0.0.10.dist-info/METADATA
PyPackIT_Test1-0.0.10.dist-info/WHEEL
PyPackIT_Test1-0.0.10.dist-info/entry_points.txt
PyPackIT_Test1-0.0.10.dist-info/top_level.txt
PyPackIT_Test1-0.0.10.dist-info/RECORD
