Metadata-Version: 2.1
Name: PyPackIT-Test1
Version: 0.0.10
Summary: A New Python Project
Author-email: Armin Ariamajd <armiariam@gmail.com>
Maintainer-email: Armin Ariamajd <armiariam@gmail.com>
License: MIT
Project-URL: Homepage, https://AAriam.github.io/PyPackIT-Test1
Project-URL: Documentation, https://AAriam.github.io/PyPackIT-Test1/manual
Project-URL: Source, https://github.com/AAriam/PyPackIT-Test1
Project-URL: Download, https://github.com/AAriam/PyPackIT-Test1/releases
Project-URL: News, https://AAriam.github.io/PyPackIT-Test1/news
Project-URL: Issue-Tracker, https://github.com/AAriam/PyPackIT-Test1/issues
Keywords: First Keyword,Second Keyword,Third Keyword,Fourth Keyword,Fifth Keyword,Sixth Keyword
Classifier: Natural Language :: English
Classifier: License :: OSI Approved :: MIT License
Classifier: Programming Language :: Python
Classifier: Programming Language :: Python :: 3 :: Only
Classifier: Programming Language :: Python :: 3.10
Classifier: Programming Language :: Python :: 3.11
Classifier: Programming Language :: Python :: 3.12
Classifier: Programming Language :: Python :: 3.13
Classifier: Operating System :: MacOS
Classifier: Operating System :: POSIX :: Linux
Classifier: Operating System :: Microsoft :: Windows
Classifier: Operating System :: OS Independent
Classifier: Development Status :: 4 - Beta
Classifier: Typing :: Typed
Requires-Python: >=3.10
License-File: LICENSES/LICENSE-MIT
Requires-Dist: pkgdata
